{
  "batch_id": "init_batch_044",
  "files": [
    {
      "file_path": "/Users/bogdan/work/leanvibe-dev/bee-hive/venv/lib/python3.12/site-packages/torch/ao/nn/quantized/reference/modules/__init__.py",
      "current_size_lines": 27,
      "has_imports": true,
      "has_version": false,
      "has_all": true,
      "preserved_content": [
        "from .conv import (",
        "from .linear import Linear",
        "from .rnn import GRU, GRUCell, LSTM, LSTMCell, RNNCell",
        "from .sparse import Embedding, EmbeddingBag",
        "__all__ = ["
      ],
      "estimated_loc_savings": 17,
      "requires_standardization": true
    },
    {
      "file_path": "/Users/bogdan/work/leanvibe-dev/bee-hive/venv/lib/python3.12/site-packages/torch/ao/nn/quantizable/modules/__init__.py",
      "current_size_lines": 7,
      "has_imports": true,
      "has_version": false,
      "has_all": true,
      "preserved_content": [
        "from .activation import MultiheadAttention",
        "from .rnn import LSTM, LSTMCell",
        "__all__ = ["
      ],
      "estimated_loc_savings": 0,
      "requires_standardization": true
    },
    {
      "file_path": "/Users/bogdan/work/leanvibe-dev/bee-hive/venv/lib/python3.12/site-packages/torch/ao/nn/intrinsic/qat/__init__.py",
      "current_size_lines": 1,
      "has_imports": true,
      "has_version": false,
      "has_all": false,
      "preserved_content": [
        "from .modules import *  # noqa: F403"
      ],
      "estimated_loc_savings": 0,
      "requires_standardization": true
    },
    {
      "file_path": "/Users/bogdan/work/leanvibe-dev/bee-hive/venv/lib/python3.12/site-packages/torch/ao/nn/intrinsic/quantized/__init__.py",
      "current_size_lines": 13,
      "has_imports": true,
      "has_version": false,
      "has_all": true,
      "preserved_content": [
        "from .modules import *  # noqa: F403",
        "__all__ = ["
      ],
      "estimated_loc_savings": 6,
      "requires_standardization": true
    },
    {
      "file_path": "/Users/bogdan/work/leanvibe-dev/bee-hive/venv/lib/python3.12/site-packages/torch/ao/nn/intrinsic/modules/__init__.py",
      "current_size_lines": 39,
      "has_imports": true,
      "has_version": false,
      "has_all": true,
      "preserved_content": [
        "from .fused import (  # noqa: F401",
        "__all__ = ["
      ],
      "estimated_loc_savings": 32,
      "requires_standardization": true
    },
    {
      "file_path": "/Users/bogdan/work/leanvibe-dev/bee-hive/venv/lib/python3.12/site-packages/torch/ao/nn/intrinsic/qat/modules/__init__.py",
      "current_size_lines": 30,
      "has_imports": true,
      "has_version": false,
      "has_all": true,
      "preserved_content": [
        "from .conv_fused import (",
        "from .linear_fused import LinearBn1d",
        "from .linear_relu import LinearReLU",
        "__all__ = ["
      ],
      "estimated_loc_savings": 21,
      "requires_standardization": true
    },
    {
      "file_path": "/Users/bogdan/work/leanvibe-dev/bee-hive/venv/lib/python3.12/site-packages/torch/ao/nn/intrinsic/quantized/dynamic/__init__.py",
      "current_size_lines": 1,
      "has_imports": true,
      "has_version": false,
      "has_all": false,
      "preserved_content": [
        "from .modules import *  # noqa: F403"
      ],
      "estimated_loc_savings": 0,
      "requires_standardization": true
    },
    {
      "file_path": "/Users/bogdan/work/leanvibe-dev/bee-hive/venv/lib/python3.12/site-packages/torch/ao/nn/intrinsic/quantized/modules/__init__.py",
      "current_size_lines": 16,
      "has_imports": true,
      "has_version": false,
      "has_all": true,
      "preserved_content": [
        "from .bn_relu import BNReLU2d, BNReLU3d",
        "from .conv_add import ConvAdd2d, ConvAddReLU2d",
        "from .conv_relu import ConvReLU1d, ConvReLU2d, ConvReLU3d",
        "from .linear_relu import LinearLeakyReLU, LinearReLU, LinearTanh",
        "__all__ = ["
      ],
      "estimated_loc_savings": 6,
      "requires_standardization": true
    },
    {
      "file_path": "/Users/bogdan/work/leanvibe-dev/bee-hive/venv/lib/python3.12/site-packages/torch/ao/nn/intrinsic/quantized/dynamic/modules/__init__.py",
      "current_size_lines": 4,
      "has_imports": true,
      "has_version": false,
      "has_all": true,
      "preserved_content": [
        "from .linear_relu import LinearReLU",
        "__all__ = ["
      ],
      "estimated_loc_savings": 0,
      "requires_standardization": true
    },
    {
      "file_path": "/Users/bogdan/work/leanvibe-dev/bee-hive/venv/lib/python3.12/site-packages/torch/ao/nn/sparse/quantized/__init__.py",
      "current_size_lines": 7,
      "has_imports": true,
      "has_version": false,
      "has_all": true,
      "preserved_content": [
        "from .linear import Linear, LinearPackedParams",
        "__all__ = ["
      ],
      "estimated_loc_savings": 0,
      "requires_standardization": true
    },
    {
      "file_path": "/Users/bogdan/work/leanvibe-dev/bee-hive/venv/lib/python3.12/site-packages/torch/ao/nn/sparse/quantized/dynamic/__init__.py",
      "current_size_lines": 4,
      "has_imports": true,
      "has_version": false,
      "has_all": true,
      "preserved_content": [
        "from .linear import Linear",
        "__all__ = ["
      ],
      "estimated_loc_savings": 0,
      "requires_standardization": true
    },
    {
      "file_path": "/Users/bogdan/work/leanvibe-dev/bee-hive/venv/lib/python3.12/site-packages/torch/ao/ns/fx/__init__.py",
      "current_size_lines": 0,
      "has_imports": false,
      "has_version": false,
      "has_all": false,
      "preserved_content": [],
      "estimated_loc_savings": 0,
      "requires_standardization": true
    },
    {
      "file_path": "/Users/bogdan/work/leanvibe-dev/bee-hive/venv/lib/python3.12/site-packages/torch/ao/quantization/backend_config/__init__.py",
      "current_size_lines": 28,
      "has_imports": true,
      "has_version": false,
      "has_all": true,
      "preserved_content": [
        "from .backend_config import (",
        "from .executorch import get_executorch_backend_config",
        "from .fbgemm import get_fbgemm_backend_config",
        "from .native import get_native_backend_config, get_native_backend_config_dict",
        "from .onednn import get_onednn_backend_config",
        "from .qnnpack import get_qnnpack_backend_config",
        "from .tensorrt import get_tensorrt_backend_config, get_tensorrt_backend_config_dict",
        "__all__ = ["
      ],
      "estimated_loc_savings": 15,
      "requires_standardization": true
    },
    {
      "file_path": "/Users/bogdan/work/leanvibe-dev/bee-hive/venv/lib/python3.12/site-packages/torch/ao/quantization/pt2e/__init__.py",
      "current_size_lines": 0,
      "has_imports": false,
      "has_version": false,
      "has_all": false,
      "preserved_content": [],
      "estimated_loc_savings": 0,
      "requires_standardization": true
    },
    {
      "file_path": "/Users/bogdan/work/leanvibe-dev/bee-hive/venv/lib/python3.12/site-packages/torch/ao/quantization/fx/__init__.py",
      "current_size_lines": 3,
      "has_imports": true,
      "has_version": false,
      "has_all": false,
      "preserved_content": [
        "from .convert import convert",
        "from .fuse import fuse",
        "from .prepare import prepare"
      ],
      "estimated_loc_savings": 0,
      "requires_standardization": true
    },
    {
      "file_path": "/Users/bogdan/work/leanvibe-dev/bee-hive/venv/lib/python3.12/site-packages/torch/ao/quantization/quantizer/__init__.py",
      "current_size_lines": 20,
      "has_imports": true,
      "has_version": false,
      "has_all": true,
      "preserved_content": [
        "from .quantizer import (",
        "__all__ = ["
      ],
      "estimated_loc_savings": 13,
      "requires_standardization": true
    },
    {
      "file_path": "/Users/bogdan/work/leanvibe-dev/bee-hive/venv/lib/python3.12/site-packages/torch/ao/quantization/pt2e/representation/__init__.py",
      "current_size_lines": 4,
      "has_imports": true,
      "has_version": false,
      "has_all": true,
      "preserved_content": [
        "from .rewrite import reference_representation_rewrite",
        "__all__ = ["
      ],
      "estimated_loc_savings": 0,
      "requires_standardization": true
    },
    {
      "file_path": "/Users/bogdan/work/leanvibe-dev/bee-hive/venv/lib/python3.12/site-packages/torch/ao/quantization/fx/_model_report/__init__.py",
      "current_size_lines": 0,
      "has_imports": false,
      "has_version": false,
      "has_all": false,
      "preserved_content": [],
      "estimated_loc_savings": 0,
      "requires_standardization": true
    },
    {
      "file_path": "/Users/bogdan/work/leanvibe-dev/bee-hive/venv/lib/python3.12/site-packages/torch/ao/pruning/sparsifier/__init__.py",
      "current_size_lines": 0,
      "has_imports": false,
      "has_version": false,
      "has_all": false,
      "preserved_content": [],
      "estimated_loc_savings": 0,
      "requires_standardization": true
    },
    {
      "file_path": "/Users/bogdan/work/leanvibe-dev/bee-hive/venv/lib/python3.12/site-packages/torch/ao/pruning/_experimental/__init__.py",
      "current_size_lines": 0,
      "has_imports": false,
      "has_version": false,
      "has_all": false,
      "preserved_content": [],
      "estimated_loc_savings": 0,
      "requires_standardization": true
    },
    {
      "file_path": "/Users/bogdan/work/leanvibe-dev/bee-hive/venv/lib/python3.12/site-packages/torch/ao/pruning/scheduler/__init__.py",
      "current_size_lines": 0,
      "has_imports": false,
      "has_version": false,
      "has_all": false,
      "preserved_content": [],
      "estimated_loc_savings": 0,
      "requires_standardization": true
    },
    {
      "file_path": "/Users/bogdan/work/leanvibe-dev/bee-hive/venv/lib/python3.12/site-packages/torch/ao/pruning/_experimental/data_sparsifier/__init__.py",
      "current_size_lines": 6,
      "has_imports": true,
      "has_version": false,
      "has_all": true,
      "preserved_content": [
        "from .base_data_sparsifier import BaseDataSparsifier",
        "from .data_norm_sparsifier import DataNormSparsifier",
        "__all__ = ["
      ],
      "estimated_loc_savings": 0,
      "requires_standardization": true
    },
    {
      "file_path": "/Users/bogdan/work/leanvibe-dev/bee-hive/venv/lib/python3.12/site-packages/torch/ao/pruning/_experimental/pruner/__init__.py",
      "current_size_lines": 5,
      "has_imports": true,
      "has_version": false,
      "has_all": false,
      "preserved_content": [
        "from .base_structured_sparsifier import BaseStructuredSparsifier",
        "from .FPGM_pruner import FPGMPruner",
        "from .lstm_saliency_pruner import LSTMSaliencyPruner",
        "from .parametrization import BiasHook, FakeStructuredSparsity",
        "from .saliency_pruner import SaliencyPruner"
      ],
      "estimated_loc_savings": 0,
      "requires_standardization": true
    },
    {
      "file_path": "/Users/bogdan/work/leanvibe-dev/bee-hive/venv/lib/python3.12/site-packages/torch/ao/pruning/_experimental/activation_sparsifier/__init__.py",
      "current_size_lines": 0,
      "has_imports": false,
      "has_version": false,
      "has_all": false,
      "preserved_content": [],
      "estimated_loc_savings": 0,
      "requires_standardization": true
    },
    {
      "file_path": "/Users/bogdan/work/leanvibe-dev/bee-hive/venv/lib/python3.12/site-packages/torch/ao/pruning/_experimental/data_scheduler/__init__.py",
      "current_size_lines": 4,
      "has_imports": true,
      "has_version": false,
      "has_all": true,
      "preserved_content": [
        "from .base_data_scheduler import BaseDataScheduler",
        "__all__ = ["
      ],
      "estimated_loc_savings": 0,
      "requires_standardization": true
    },
    {
      "file_path": "/Users/bogdan/work/leanvibe-dev/bee-hive/venv/lib/python3.12/site-packages/torch/ao/pruning/_experimental/data_sparsifier/lightning/__init__.py",
      "current_size_lines": 0,
      "has_imports": false,
      "has_version": false,
      "has_all": false,
      "preserved_content": [],
      "estimated_loc_savings": 0,
      "requires_standardization": true
    },
    {
      "file_path": "/Users/bogdan/work/leanvibe-dev/bee-hive/venv/lib/python3.12/site-packages/torch/ao/pruning/_experimental/data_sparsifier/lightning/callbacks/__init__.py",
      "current_size_lines": 0,
      "has_imports": false,
      "has_version": false,
      "has_all": false,
      "preserved_content": [],
      "estimated_loc_savings": 0,
      "requires_standardization": true
    },
    {
      "file_path": "/Users/bogdan/work/leanvibe-dev/bee-hive/venv/lib/python3.12/site-packages/torch/_refs/linalg/__init__.py",
      "current_size_lines": 295,
      "has_imports": true,
      "has_version": false,
      "has_all": true,
      "preserved_content": [
        "__all__ = ["
      ],
      "estimated_loc_savings": 289,
      "requires_standardization": true
    },
    {
      "file_path": "/Users/bogdan/work/leanvibe-dev/bee-hive/venv/lib/python3.12/site-packages/torch/_refs/nn/__init__.py",
      "current_size_lines": 1,
      "has_imports": false,
      "has_version": false,
      "has_all": true,
      "preserved_content": [
        "__all__: list[str] = []"
      ],
      "estimated_loc_savings": 0,
      "requires_standardization": true
    },
    {
      "file_path": "/Users/bogdan/work/leanvibe-dev/bee-hive/venv/lib/python3.12/site-packages/torch/_refs/special/__init__.py",
      "current_size_lines": 195,
      "has_imports": true,
      "has_version": false,
      "has_all": true,
      "preserved_content": [
        "__all__ = ["
      ],
      "estimated_loc_savings": 189,
      "requires_standardization": true
    },
    {
      "file_path": "/Users/bogdan/work/leanvibe-dev/bee-hive/venv/lib/python3.12/site-packages/torch/_refs/nn/functional/__init__.py",
      "current_size_lines": 1119,
      "has_imports": true,
      "has_version": false,
      "has_all": true,
      "preserved_content": [
        "__all__ = ["
      ],
      "estimated_loc_savings": 1113,
      "requires_standardization": true
    },
    {
      "file_path": "/Users/bogdan/work/leanvibe-dev/bee-hive/venv/lib/python3.12/site-packages/torch/export/experimental/__init__.py",
      "current_size_lines": 266,
      "has_imports": true,
      "has_version": false,
      "has_all": false,
      "preserved_content": [],
      "estimated_loc_savings": 261,
      "requires_standardization": true
    },
    {
      "file_path": "/Users/bogdan/work/leanvibe-dev/bee-hive/venv/lib/python3.12/site-packages/torch/export/passes/__init__.py",
      "current_size_lines": 58,
      "has_imports": true,
      "has_version": false,
      "has_all": true,
      "preserved_content": [
        "__all__ = [\"move_to_device_pass\"]"
      ],
      "estimated_loc_savings": 52,
      "requires_standardization": true
    },
    {
      "file_path": "/Users/bogdan/work/leanvibe-dev/bee-hive/venv/lib/python3.12/site-packages/torch/export/pt2_archive/__init__.py",
      "current_size_lines": 2,
      "has_imports": true,
      "has_version": false,
      "has_all": true,
      "preserved_content": [
        "from ._package import is_pt2_package, PT2ArchiveReader, PT2ArchiveWriter",
        "__all__ = [\"PT2ArchiveWriter\", \"PT2ArchiveReader\", \"is_pt2_package\"]"
      ],
      "estimated_loc_savings": 0,
      "requires_standardization": true
    },
    {
      "file_path": "/Users/bogdan/work/leanvibe-dev/bee-hive/venv/lib/python3.12/site-packages/torch/nested/_internal/__init__.py",
      "current_size_lines": 0,
      "has_imports": false,
      "has_version": false,
      "has_all": false,
      "preserved_content": [],
      "estimated_loc_savings": 0,
      "requires_standardization": true
    },
    {
      "file_path": "/Users/bogdan/work/leanvibe-dev/bee-hive/venv/lib/python3.12/site-packages/torch/signal/windows/__init__.py",
      "current_size_lines": 26,
      "has_imports": true,
      "has_version": false,
      "has_all": true,
      "preserved_content": [
        "from .windows import (",
        "__all__ = ["
      ],
      "estimated_loc_savings": 19,
      "requires_standardization": true
    },
    {
      "file_path": "/Users/bogdan/work/leanvibe-dev/bee-hive/venv/lib/python3.12/site-packages/torch/package/analyze/__init__.py",
      "current_size_lines": 2,
      "has_imports": true,
      "has_version": false,
      "has_all": false,
      "preserved_content": [
        "from .find_first_use_of_broken_modules import find_first_use_of_broken_modules",
        "from .trace_dependencies import trace_dependencies"
      ],
      "estimated_loc_savings": 0,
      "requires_standardization": true
    },
    {
      "file_path": "/Users/bogdan/work/leanvibe-dev/bee-hive/venv/lib/python3.12/site-packages/zipp/compat/__init__.py",
      "current_size_lines": 0,
      "has_imports": false,
      "has_version": false,
      "has_all": false,
      "preserved_content": [],
      "estimated_loc_savings": 0,
      "requires_standardization": true
    },
    {
      "file_path": "/Users/bogdan/work/leanvibe-dev/bee-hive/venv/lib/python3.12/site-packages/websockets/legacy/__init__.py",
      "current_size_lines": 8,
      "has_imports": true,
      "has_version": false,
      "has_all": false,
      "preserved_content": [],
      "estimated_loc_savings": 3,
      "requires_standardization": true
    },
    {
      "file_path": "/Users/bogdan/work/leanvibe-dev/bee-hive/venv/lib/python3.12/site-packages/websockets/extensions/__init__.py",
      "current_size_lines": 2,
      "has_imports": true,
      "has_version": false,
      "has_all": true,
      "preserved_content": [
        "from .base import *",
        "__all__ = [\"Extension\", \"ClientExtensionFactory\", \"ServerExtensionFactory\"]"
      ],
      "estimated_loc_savings": 0,
      "requires_standardization": true
    },
    {
      "file_path": "/Users/bogdan/work/leanvibe-dev/bee-hive/venv/lib/python3.12/site-packages/websockets/sync/__init__.py",
      "current_size_lines": 0,
      "has_imports": false,
      "has_version": false,
      "has_all": false,
      "preserved_content": [],
      "estimated_loc_savings": 0,
      "requires_standardization": true
    },
    {
      "file_path": "/Users/bogdan/work/leanvibe-dev/bee-hive/venv/lib/python3.12/site-packages/websockets/asyncio/__init__.py",
      "current_size_lines": 0,
      "has_imports": false,
      "has_version": false,
      "has_all": false,
      "preserved_content": [],
      "estimated_loc_savings": 0,
      "requires_standardization": true
    },
    {
      "file_path": "/Users/bogdan/work/leanvibe-dev/bee-hive/venv/lib/python3.12/site-packages/faker/providers/__init__.py",
      "current_size_lines": 644,
      "has_imports": true,
      "has_version": false,
      "has_all": false,
      "preserved_content": [
        "from ..generator import Generator",
        "from ..typing import OrderedDictType",
        "from ..utils.distribution import choices_distribution, choices_distribution_unique"
      ],
      "estimated_loc_savings": 636,
      "requires_standardization": true
    },
    {
      "file_path": "/Users/bogdan/work/leanvibe-dev/bee-hive/venv/lib/python3.12/site-packages/faker/utils/__init__.py",
      "current_size_lines": 0,
      "has_imports": false,
      "has_version": false,
      "has_all": false,
      "preserved_content": [],
      "estimated_loc_savings": 0,
      "requires_standardization": true
    },
    {
      "file_path": "/Users/bogdan/work/leanvibe-dev/bee-hive/venv/lib/python3.12/site-packages/faker/contrib/__init__.py",
      "current_size_lines": 0,
      "has_imports": false,
      "has_version": false,
      "has_all": false,
      "preserved_content": [],
      "estimated_loc_savings": 0,
      "requires_standardization": true
    },
    {
      "file_path": "/Users/bogdan/work/leanvibe-dev/bee-hive/venv/lib/python3.12/site-packages/faker/decode/__init__.py",
      "current_size_lines": 10,
      "has_imports": true,
      "has_version": false,
      "has_all": false,
      "preserved_content": [
        "from .codes import codes"
      ],
      "estimated_loc_savings": 4,
      "requires_standardization": true
    },
    {
      "file_path": "/Users/bogdan/work/leanvibe-dev/bee-hive/venv/lib/python3.12/site-packages/faker/sphinx/__init__.py",
      "current_size_lines": 0,
      "has_imports": false,
      "has_version": false,
      "has_all": false,
      "preserved_content": [],
      "estimated_loc_savings": 0,
      "requires_standardization": true
    },
    {
      "file_path": "/Users/bogdan/work/leanvibe-dev/bee-hive/venv/lib/python3.12/site-packages/faker/providers/misc/__init__.py",
      "current_size_lines": 636,
      "has_imports": true,
      "has_version": false,
      "has_all": false,
      "preserved_content": [
        "from .. import BaseProvider",
        "from ..python import TypesSpec"
      ],
      "estimated_loc_savings": 629,
      "requires_standardization": true
    },
    {
      "file_path": "/Users/bogdan/work/leanvibe-dev/bee-hive/venv/lib/python3.12/site-packages/faker/providers/user_agent/__init__.py",
      "current_size_lines": 330,
      "has_imports": true,
      "has_version": false,
      "has_all": false,
      "preserved_content": [
        "from .. import BaseProvider, ElementsType"
      ],
      "estimated_loc_savings": 324,
      "requires_standardization": true
    },
    {
      "file_path": "/Users/bogdan/work/leanvibe-dev/bee-hive/venv/lib/python3.12/site-packages/faker/providers/credit_card/__init__.py",
      "current_size_lines": 173,
      "has_imports": true,
      "has_version": false,
      "has_all": false,
      "preserved_content": [
        "from ...typing import CardType, CreditCard, DateParseType",
        "from .. import BaseProvider"
      ],
      "estimated_loc_savings": 166,
      "requires_standardization": true
    }
  ],
  "estimated_loc_savings": 3795,
  "file_count": 50
}