{
  "batch_id": "init_batch_013",
  "files": [
    {
      "file_path": "/Users/bogdan/work/leanvibe-dev/bee-hive/.venv/lib/python3.13/site-packages/authlib/oidc/core/__init__.py",
      "current_size_lines": 31,
      "has_imports": true,
      "has_version": false,
      "has_all": true,
      "preserved_content": [
        "from .claims import CodeIDToken",
        "from .claims import HybridIDToken",
        "from .claims import IDToken",
        "from .claims import ImplicitIDToken",
        "from .claims import UserInfo",
        "from .claims import get_claim_cls_by_response_type",
        "from .grants import OpenIDCode",
        "from .grants import OpenIDHybridGrant",
        "from .grants import OpenIDImplicitGrant",
        "from .grants import OpenIDToken",
        "from .models import AuthorizationCodeMixin",
        "from .userinfo import UserInfoEndpoint",
        "__all__ = ["
      ],
      "estimated_loc_savings": 13,
      "requires_standardization": true
    },
    {
      "file_path": "/Users/bogdan/work/leanvibe-dev/bee-hive/.venv/lib/python3.13/site-packages/authlib/oidc/discovery/__init__.py",
      "current_size_lines": 8,
      "has_imports": true,
      "has_version": false,
      "has_all": true,
      "preserved_content": [
        "from .models import OpenIDProviderMetadata",
        "from .well_known import get_well_known_url",
        "__all__ = [\"OpenIDProviderMetadata\", \"get_well_known_url\"]"
      ],
      "estimated_loc_savings": 0,
      "requires_standardization": true
    },
    {
      "file_path": "/Users/bogdan/work/leanvibe-dev/bee-hive/.venv/lib/python3.13/site-packages/authlib/oidc/core/grants/__init__.py",
      "current_size_lines": 10,
      "has_imports": true,
      "has_version": false,
      "has_all": true,
      "preserved_content": [
        "from .code import OpenIDCode",
        "from .code import OpenIDToken",
        "from .hybrid import OpenIDHybridGrant",
        "from .implicit import OpenIDImplicitGrant",
        "__all__ = ["
      ],
      "estimated_loc_savings": 0,
      "requires_standardization": true
    },
    {
      "file_path": "/Users/bogdan/work/leanvibe-dev/bee-hive/.venv/lib/python3.13/site-packages/authlib/jose/rfc7519/__init__.py",
      "current_size_lines": 10,
      "has_imports": true,
      "has_version": false,
      "has_all": true,
      "preserved_content": [
        "from .claims import BaseClaims",
        "from .claims import JWTClaims",
        "from .jwt import JsonWebToken",
        "__all__ = [\"JsonWebToken\", \"BaseClaims\", \"JWTClaims\"]"
      ],
      "estimated_loc_savings": 1,
      "requires_standardization": true
    },
    {
      "file_path": "/Users/bogdan/work/leanvibe-dev/bee-hive/.venv/lib/python3.13/site-packages/authlib/jose/rfc7517/__init__.py",
      "current_size_lines": 12,
      "has_imports": true,
      "has_version": false,
      "has_all": true,
      "preserved_content": [
        "from ._cryptography_key import load_pem_key",
        "from .asymmetric_key import AsymmetricKey",
        "from .base_key import Key",
        "from .jwk import JsonWebKey",
        "from .key_set import KeySet",
        "__all__ = [\"Key\", \"AsymmetricKey\", \"KeySet\", \"JsonWebKey\", \"load_pem_key\"]"
      ],
      "estimated_loc_savings": 1,
      "requires_standardization": true
    },
    {
      "file_path": "/Users/bogdan/work/leanvibe-dev/bee-hive/.venv/lib/python3.13/site-packages/authlib/jose/rfc7516/__init__.py",
      "current_size_lines": 18,
      "has_imports": true,
      "has_version": false,
      "has_all": true,
      "preserved_content": [
        "from .jwe import JsonWebEncryption",
        "from .models import JWEAlgorithm",
        "from .models import JWEAlgorithmWithTagAwareKeyAgreement",
        "from .models import JWEEncAlgorithm",
        "from .models import JWEZipAlgorithm",
        "__all__ = ["
      ],
      "estimated_loc_savings": 7,
      "requires_standardization": true
    },
    {
      "file_path": "/Users/bogdan/work/leanvibe-dev/bee-hive/.venv/lib/python3.13/site-packages/authlib/jose/rfc7518/__init__.py",
      "current_size_lines": 31,
      "has_imports": true,
      "has_version": false,
      "has_all": true,
      "preserved_content": [
        "from .ec_key import ECKey",
        "from .jwe_algs import JWE_ALG_ALGORITHMS",
        "from .jwe_algs import AESAlgorithm",
        "from .jwe_algs import ECDHESAlgorithm",
        "from .jwe_algs import u32be_len_input",
        "from .jwe_encs import JWE_ENC_ALGORITHMS",
        "from .jwe_encs import CBCHS2EncAlgorithm",
        "from .jwe_zips import DeflateZipAlgorithm",
        "from .jws_algs import JWS_ALGORITHMS",
        "from .oct_key import OctKey",
        "from .rsa_key import RSAKey",
        "__all__ = ["
      ],
      "estimated_loc_savings": 14,
      "requires_standardization": true
    },
    {
      "file_path": "/Users/bogdan/work/leanvibe-dev/bee-hive/.venv/lib/python3.13/site-packages/authlib/jose/drafts/__init__.py",
      "current_size_lines": 13,
      "has_imports": true,
      "has_version": false,
      "has_all": true,
      "preserved_content": [
        "from ._jwe_algorithms import JWE_DRAFT_ALG_ALGORITHMS",
        "from ._jwe_enc_cryptography import C20PEncAlgorithm",
        "    from ._jwe_enc_cryptodome import XC20PEncAlgorithm",
        "__all__ = [\"register_jwe_draft\"]"
      ],
      "estimated_loc_savings": 4,
      "requires_standardization": true
    },
    {
      "file_path": "/Users/bogdan/work/leanvibe-dev/bee-hive/.venv/lib/python3.13/site-packages/authlib/jose/rfc8037/__init__.py",
      "current_size_lines": 3,
      "has_imports": true,
      "has_version": false,
      "has_all": true,
      "preserved_content": [
        "from .jws_eddsa import register_jws_rfc8037",
        "from .okp_key import OKPKey",
        "__all__ = [\"register_jws_rfc8037\", \"OKPKey\"]"
      ],
      "estimated_loc_savings": 0,
      "requires_standardization": true
    },
    {
      "file_path": "/Users/bogdan/work/leanvibe-dev/bee-hive/.venv/lib/python3.13/site-packages/authlib/jose/rfc7515/__init__.py",
      "current_size_lines": 11,
      "has_imports": true,
      "has_version": false,
      "has_all": true,
      "preserved_content": [
        "from .jws import JsonWebSignature",
        "from .models import JWSAlgorithm",
        "from .models import JWSHeader",
        "from .models import JWSObject",
        "__all__ = [\"JsonWebSignature\", \"JWSAlgorithm\", \"JWSHeader\", \"JWSObject\"]"
      ],
      "estimated_loc_savings": 1,
      "requires_standardization": true
    },
    {
      "file_path": "/Users/bogdan/work/leanvibe-dev/bee-hive/.venv/lib/python3.13/site-packages/authlib/integrations/flask_oauth2/__init__.py",
      "current_size_lines": 7,
      "has_imports": true,
      "has_version": false,
      "has_all": false,
      "preserved_content": [
        "from .authorization_server import AuthorizationServer",
        "from .resource_protector import ResourceProtector",
        "from .resource_protector import current_token",
        "from .signals import client_authenticated",
        "from .signals import token_authenticated",
        "from .signals import token_revoked"
      ],
      "estimated_loc_savings": 0,
      "requires_standardization": true
    },
    {
      "file_path": "/Users/bogdan/work/leanvibe-dev/bee-hive/.venv/lib/python3.13/site-packages/authlib/integrations/base_client/__init__.py",
      "current_size_lines": 28,
      "has_imports": true,
      "has_version": false,
      "has_all": true,
      "preserved_content": [
        "from .errors import InvalidTokenError",
        "from .errors import MismatchingStateError",
        "from .errors import MissingRequestTokenError",
        "from .errors import MissingTokenError",
        "from .errors import OAuthError",
        "from .errors import TokenExpiredError",
        "from .errors import UnsupportedTokenTypeError",
        "from .framework_integration import FrameworkIntegration",
        "from .registry import BaseOAuth",
        "from .sync_app import BaseApp",
        "from .sync_app import OAuth1Mixin",
        "from .sync_app import OAuth2Mixin",
        "from .sync_openid import OpenIDMixin",
        "__all__ = ["
      ],
      "estimated_loc_savings": 9,
      "requires_standardization": true
    },
    {
      "file_path": "/Users/bogdan/work/leanvibe-dev/bee-hive/.venv/lib/python3.13/site-packages/authlib/integrations/requests_client/__init__.py",
      "current_size_lines": 26,
      "has_imports": true,
      "has_version": false,
      "has_all": true,
      "preserved_content": [
        "from ..base_client import OAuthError",
        "from .assertion_session import AssertionSession",
        "from .oauth1_session import OAuth1Auth",
        "from .oauth1_session import OAuth1Session",
        "from .oauth2_session import OAuth2Auth",
        "from .oauth2_session import OAuth2Session",
        "__all__ = ["
      ],
      "estimated_loc_savings": 14,
      "requires_standardization": true
    },
    {
      "file_path": "/Users/bogdan/work/leanvibe-dev/bee-hive/.venv/lib/python3.13/site-packages/authlib/integrations/django_oauth2/__init__.py",
      "current_size_lines": 8,
      "has_imports": true,
      "has_version": false,
      "has_all": false,
      "preserved_content": [
        "from .authorization_server import AuthorizationServer",
        "from .endpoints import RevocationEndpoint",
        "from .resource_protector import BearerTokenValidator",
        "from .resource_protector import ResourceProtector",
        "from .signals import client_authenticated",
        "from .signals import token_authenticated",
        "from .signals import token_revoked"
      ],
      "estimated_loc_savings": 0,
      "requires_standardization": true
    },
    {
      "file_path": "/Users/bogdan/work/leanvibe-dev/bee-hive/.venv/lib/python3.13/site-packages/authlib/integrations/sqla_oauth2/__init__.py",
      "current_size_lines": 18,
      "has_imports": true,
      "has_version": false,
      "has_all": true,
      "preserved_content": [
        "from .client_mixin import OAuth2ClientMixin",
        "from .functions import create_bearer_token_validator",
        "from .functions import create_query_client_func",
        "from .functions import create_query_token_func",
        "from .functions import create_revocation_endpoint",
        "from .functions import create_save_token_func",
        "from .tokens_mixins import OAuth2AuthorizationCodeMixin",
        "from .tokens_mixins import OAuth2TokenMixin",
        "__all__ = ["
      ],
      "estimated_loc_savings": 4,
      "requires_standardization": true
    },
    {
      "file_path": "/Users/bogdan/work/leanvibe-dev/bee-hive/.venv/lib/python3.13/site-packages/authlib/integrations/starlette_client/__init__.py",
      "current_size_lines": 21,
      "has_imports": true,
      "has_version": false,
      "has_all": true,
      "preserved_content": [
        "from ..base_client import BaseOAuth",
        "from ..base_client import OAuthError",
        "from .apps import StarletteOAuth1App",
        "from .apps import StarletteOAuth2App",
        "from .integration import StarletteIntegration",
        "__all__ = ["
      ],
      "estimated_loc_savings": 10,
      "requires_standardization": true
    },
    {
      "file_path": "/Users/bogdan/work/leanvibe-dev/bee-hive/.venv/lib/python3.13/site-packages/authlib/integrations/flask_client/__init__.py",
      "current_size_lines": 48,
      "has_imports": true,
      "has_version": false,
      "has_all": true,
      "preserved_content": [
        "from ..base_client import BaseOAuth",
        "from ..base_client import OAuthError",
        "from .apps import FlaskOAuth1App",
        "from .apps import FlaskOAuth2App",
        "from .integration import FlaskIntegration",
        "from .integration import token_update",
        "__all__ = ["
      ],
      "estimated_loc_savings": 36,
      "requires_standardization": true
    },
    {
      "file_path": "/Users/bogdan/work/leanvibe-dev/bee-hive/.venv/lib/python3.13/site-packages/authlib/integrations/flask_oauth1/__init__.py",
      "current_size_lines": 7,
      "has_imports": true,
      "has_version": false,
      "has_all": false,
      "preserved_content": [
        "from .authorization_server import AuthorizationServer",
        "from .cache import create_exists_nonce_func",
        "from .cache import register_nonce_hooks",
        "from .cache import register_temporary_credential_hooks",
        "from .resource_protector import ResourceProtector",
        "from .resource_protector import current_credential"
      ],
      "estimated_loc_savings": 0,
      "requires_standardization": true
    },
    {
      "file_path": "/Users/bogdan/work/leanvibe-dev/bee-hive/.venv/lib/python3.13/site-packages/authlib/integrations/httpx_client/__init__.py",
      "current_size_lines": 34,
      "has_imports": true,
      "has_version": false,
      "has_all": true,
      "preserved_content": [
        "from ..base_client import OAuthError",
        "from .assertion_client import AssertionClient",
        "from .assertion_client import AsyncAssertionClient",
        "from .oauth1_client import AsyncOAuth1Client",
        "from .oauth1_client import OAuth1Auth",
        "from .oauth1_client import OAuth1Client",
        "from .oauth2_client import AsyncOAuth2Client",
        "from .oauth2_client import OAuth2Auth",
        "from .oauth2_client import OAuth2Client",
        "from .oauth2_client import OAuth2ClientAuth",
        "__all__ = ["
      ],
      "estimated_loc_savings": 18,
      "requires_standardization": true
    },
    {
      "file_path": "/Users/bogdan/work/leanvibe-dev/bee-hive/.venv/lib/python3.13/site-packages/authlib/integrations/django_oauth1/__init__.py",
      "current_size_lines": 4,
      "has_imports": true,
      "has_version": false,
      "has_all": true,
      "preserved_content": [
        "from .authorization_server import BaseServer",
        "from .authorization_server import CacheAuthorizationServer",
        "from .resource_protector import ResourceProtector",
        "__all__ = [\"BaseServer\", \"CacheAuthorizationServer\", \"ResourceProtector\"]"
      ],
      "estimated_loc_savings": 0,
      "requires_standardization": true
    },
    {
      "file_path": "/Users/bogdan/work/leanvibe-dev/bee-hive/.venv/lib/python3.13/site-packages/authlib/integrations/django_client/__init__.py",
      "current_size_lines": 18,
      "has_imports": true,
      "has_version": false,
      "has_all": true,
      "preserved_content": [
        "from ..base_client import BaseOAuth",
        "from ..base_client import OAuthError",
        "from .apps import DjangoOAuth1App",
        "from .apps import DjangoOAuth2App",
        "from .integration import DjangoIntegration",
        "from .integration import token_update",
        "__all__ = ["
      ],
      "estimated_loc_savings": 6,
      "requires_standardization": true
    },
    {
      "file_path": "/Users/bogdan/work/leanvibe-dev/bee-hive/.venv/lib/python3.13/site-packages/authlib/oauth1/rfc5849/__init__.py",
      "current_size_lines": 35,
      "has_imports": true,
      "has_version": false,
      "has_all": true,
      "preserved_content": [
        "from .authorization_server import AuthorizationServer",
        "from .client_auth import ClientAuth",
        "from .models import ClientMixin",
        "from .models import TemporaryCredential",
        "from .models import TemporaryCredentialMixin",
        "from .models import TokenCredentialMixin",
        "from .resource_protector import ResourceProtector",
        "from .signature import SIGNATURE_HMAC_SHA1",
        "from .signature import SIGNATURE_PLAINTEXT",
        "from .signature import SIGNATURE_RSA_SHA1",
        "from .signature import SIGNATURE_TYPE_BODY",
        "from .signature import SIGNATURE_TYPE_HEADER",
        "from .signature import SIGNATURE_TYPE_QUERY",
        "from .wrapper import OAuth1Request",
        "__all__ = ["
      ],
      "estimated_loc_savings": 15,
      "requires_standardization": true
    },
    {
      "file_path": "/Users/bogdan/work/leanvibe-dev/bee-hive/.venv/lib/python3.13/site-packages/greenlet/platform/__init__.py",
      "current_size_lines": 0,
      "has_imports": false,
      "has_version": false,
      "has_all": false,
      "preserved_content": [],
      "estimated_loc_savings": 0,
      "requires_standardization": true
    },
    {
      "file_path": "/Users/bogdan/work/leanvibe-dev/bee-hive/.venv/lib/python3.13/site-packages/greenlet/tests/__init__.py",
      "current_size_lines": 217,
      "has_imports": true,
      "has_version": false,
      "has_all": false,
      "preserved_content": [
        "from . import leakcheck"
      ],
      "estimated_loc_savings": 211,
      "requires_standardization": true
    },
    {
      "file_path": "/Users/bogdan/work/leanvibe-dev/bee-hive/.venv/lib/python3.13/site-packages/pydantic/v1/__init__.py",
      "current_size_lines": 129,
      "has_imports": true,
      "has_version": true,
      "has_all": true,
      "preserved_content": [
        "__version__ = VERSION",
        "__all__ = ["
      ],
      "estimated_loc_savings": 122,
      "requires_standardization": true
    },
    {
      "file_path": "/Users/bogdan/work/leanvibe-dev/bee-hive/.venv/lib/python3.13/site-packages/pydantic/_internal/__init__.py",
      "current_size_lines": 0,
      "has_imports": false,
      "has_version": false,
      "has_all": false,
      "preserved_content": [],
      "estimated_loc_savings": 0,
      "requires_standardization": true
    },
    {
      "file_path": "/Users/bogdan/work/leanvibe-dev/bee-hive/.venv/lib/python3.13/site-packages/pydantic/plugin/__init__.py",
      "current_size_lines": 130,
      "has_imports": true,
      "has_version": false,
      "has_all": true,
      "preserved_content": [
        "__all__ = ("
      ],
      "estimated_loc_savings": 124,
      "requires_standardization": true
    },
    {
      "file_path": "/Users/bogdan/work/leanvibe-dev/bee-hive/.venv/lib/python3.13/site-packages/pydantic/deprecated/__init__.py",
      "current_size_lines": 0,
      "has_imports": false,
      "has_version": false,
      "has_all": false,
      "preserved_content": [],
      "estimated_loc_savings": 0,
      "requires_standardization": true
    },
    {
      "file_path": "/Users/bogdan/work/leanvibe-dev/bee-hive/.venv/lib/python3.13/site-packages/dns/rdtypes/__init__.py",
      "current_size_lines": 30,
      "has_imports": false,
      "has_version": false,
      "has_all": true,
      "preserved_content": [
        "__all__ = ["
      ],
      "estimated_loc_savings": 24,
      "requires_standardization": true
    },
    {
      "file_path": "/Users/bogdan/work/leanvibe-dev/bee-hive/.venv/lib/python3.13/site-packages/dns/dnssecalgs/__init__.py",
      "current_size_lines": 99,
      "has_imports": true,
      "has_version": false,
      "has_all": false,
      "preserved_content": [],
      "estimated_loc_savings": 94,
      "requires_standardization": true
    },
    {
      "file_path": "/Users/bogdan/work/leanvibe-dev/bee-hive/.venv/lib/python3.13/site-packages/dns/quic/__init__.py",
      "current_size_lines": 57,
      "has_imports": true,
      "has_version": false,
      "has_all": false,
      "preserved_content": [],
      "estimated_loc_savings": 52,
      "requires_standardization": true
    },
    {
      "file_path": "/Users/bogdan/work/leanvibe-dev/bee-hive/.venv/lib/python3.13/site-packages/dns/rdtypes/IN/__init__.py",
      "current_size_lines": 32,
      "has_imports": false,
      "has_version": false,
      "has_all": true,
      "preserved_content": [
        "__all__ = ["
      ],
      "estimated_loc_savings": 26,
      "requires_standardization": true
    },
    {
      "file_path": "/Users/bogdan/work/leanvibe-dev/bee-hive/.venv/lib/python3.13/site-packages/dns/rdtypes/CH/__init__.py",
      "current_size_lines": 19,
      "has_imports": false,
      "has_version": false,
      "has_all": true,
      "preserved_content": [
        "__all__ = ["
      ],
      "estimated_loc_savings": 13,
      "requires_standardization": true
    },
    {
      "file_path": "/Users/bogdan/work/leanvibe-dev/bee-hive/.venv/lib/python3.13/site-packages/dns/rdtypes/ANY/__init__.py",
      "current_size_lines": 67,
      "has_imports": false,
      "has_version": false,
      "has_all": true,
      "preserved_content": [
        "__all__ = ["
      ],
      "estimated_loc_savings": 61,
      "requires_standardization": true
    },
    {
      "file_path": "/Users/bogdan/work/leanvibe-dev/bee-hive/.venv/lib/python3.13/site-packages/billiard/dummy/__init__.py",
      "current_size_lines": 123,
      "has_imports": true,
      "has_version": false,
      "has_all": true,
      "preserved_content": [
        "__all__ = ["
      ],
      "estimated_loc_savings": 117,
      "requires_standardization": true
    },
    {
      "file_path": "/Users/bogdan/work/leanvibe-dev/bee-hive/.venv/lib/python3.13/site-packages/psutil/tests/__init__.py",
      "current_size_lines": 1823,
      "has_imports": true,
      "has_version": true,
      "has_all": true,
      "preserved_content": [
        "__all__ = [",
        "    info['pip'] = getattr(pip, '__version__', 'not installed')",
        "        info['pip'] += \" (wheel=%s)\" % wheel.__version__"
      ],
      "estimated_loc_savings": 1815,
      "requires_standardization": true
    },
    {
      "file_path": "/Users/bogdan/work/leanvibe-dev/bee-hive/.venv/lib/python3.13/site-packages/apscheduler/triggers/__init__.py",
      "current_size_lines": 0,
      "has_imports": false,
      "has_version": false,
      "has_all": false,
      "preserved_content": [],
      "estimated_loc_savings": 0,
      "requires_standardization": true
    },
    {
      "file_path": "/Users/bogdan/work/leanvibe-dev/bee-hive/.venv/lib/python3.13/site-packages/apscheduler/executors/__init__.py",
      "current_size_lines": 0,
      "has_imports": false,
      "has_version": false,
      "has_all": false,
      "preserved_content": [],
      "estimated_loc_savings": 0,
      "requires_standardization": true
    },
    {
      "file_path": "/Users/bogdan/work/leanvibe-dev/bee-hive/.venv/lib/python3.13/site-packages/apscheduler/jobstores/__init__.py",
      "current_size_lines": 0,
      "has_imports": false,
      "has_version": false,
      "has_all": false,
      "preserved_content": [],
      "estimated_loc_savings": 0,
      "requires_standardization": true
    },
    {
      "file_path": "/Users/bogdan/work/leanvibe-dev/bee-hive/.venv/lib/python3.13/site-packages/apscheduler/schedulers/__init__.py",
      "current_size_lines": 8,
      "has_imports": false,
      "has_version": false,
      "has_all": false,
      "preserved_content": [],
      "estimated_loc_savings": 3,
      "requires_standardization": true
    },
    {
      "file_path": "/Users/bogdan/work/leanvibe-dev/bee-hive/.venv/lib/python3.13/site-packages/apscheduler/triggers/cron/__init__.py",
      "current_size_lines": 252,
      "has_imports": true,
      "has_version": false,
      "has_all": false,
      "preserved_content": [],
      "estimated_loc_savings": 247,
      "requires_standardization": true
    },
    {
      "file_path": "/Users/bogdan/work/leanvibe-dev/bee-hive/.venv/lib/python3.13/site-packages/pbr/cmd/__init__.py",
      "current_size_lines": 0,
      "has_imports": false,
      "has_version": false,
      "has_all": false,
      "preserved_content": [],
      "estimated_loc_savings": 0,
      "requires_standardization": true
    },
    {
      "file_path": "/Users/bogdan/work/leanvibe-dev/bee-hive/.venv/lib/python3.13/site-packages/pbr/tests/__init__.py",
      "current_size_lines": 24,
      "has_imports": true,
      "has_version": false,
      "has_all": false,
      "preserved_content": [],
      "estimated_loc_savings": 19,
      "requires_standardization": true
    },
    {
      "file_path": "/Users/bogdan/work/leanvibe-dev/bee-hive/.venv/lib/python3.13/site-packages/pbr/hooks/__init__.py",
      "current_size_lines": 27,
      "has_imports": true,
      "has_version": false,
      "has_all": false,
      "preserved_content": [],
      "estimated_loc_savings": 22,
      "requires_standardization": true
    },
    {
      "file_path": "/Users/bogdan/work/leanvibe-dev/bee-hive/.venv/lib/python3.13/site-packages/pbr/_compat/__init__.py",
      "current_size_lines": 0,
      "has_imports": false,
      "has_version": false,
      "has_all": false,
      "preserved_content": [],
      "estimated_loc_savings": 0,
      "requires_standardization": true
    },
    {
      "file_path": "/Users/bogdan/work/leanvibe-dev/bee-hive/.venv/lib/python3.13/site-packages/pbr/tests/_compat/__init__.py",
      "current_size_lines": 0,
      "has_imports": false,
      "has_version": false,
      "has_all": false,
      "preserved_content": [],
      "estimated_loc_savings": 0,
      "requires_standardization": true
    },
    {
      "file_path": "/Users/bogdan/work/leanvibe-dev/bee-hive/.venv/lib/python3.13/site-packages/pbr/tests/functional/__init__.py",
      "current_size_lines": 0,
      "has_imports": false,
      "has_version": false,
      "has_all": false,
      "preserved_content": [],
      "estimated_loc_savings": 0,
      "requires_standardization": true
    },
    {
      "file_path": "/Users/bogdan/work/leanvibe-dev/bee-hive/.venv/lib/python3.13/site-packages/pbr/tests/testpackage/pbr_testpackage/__init__.py",
      "current_size_lines": 2,
      "has_imports": true,
      "has_version": true,
      "has_all": false,
      "preserved_content": [
        "__version__ = pbr.version.VersionInfo('pbr_testpackage').version_string()"
      ],
      "estimated_loc_savings": 0,
      "requires_standardization": true
    },
    {
      "file_path": "/Users/bogdan/work/leanvibe-dev/bee-hive/.venv/lib/python3.13/site-packages/gitdb/test/__init__.py",
      "current_size_lines": 4,
      "has_imports": false,
      "has_version": false,
      "has_all": false,
      "preserved_content": [],
      "estimated_loc_savings": 0,
      "requires_standardization": true
    },
    {
      "file_path": "/Users/bogdan/work/leanvibe-dev/bee-hive/.venv/lib/python3.13/site-packages/gitdb/utils/__init__.py",
      "current_size_lines": 0,
      "has_imports": false,
      "has_version": false,
      "has_all": false,
      "preserved_content": [],
      "estimated_loc_savings": 0,
      "requires_standardization": true
    }
  ],
  "estimated_loc_savings": 3103,
  "file_count": 50
}